{"__symbolic":"module","version":4,"metadata":{"RandomerService":{"__symbolic":"class","decorators":[{"__symbolic":"call","expression":{"__symbolic":"reference","module":"@angular/core","name":"Injectable","line":2,"character":1},"arguments":[{"providedIn":"root"}]}],"members":{"__ctor__":[{"__symbolic":"constructor"}]},"statics":{"ngInjectableDef":{}}},"RandomerComponent":{"__symbolic":"class","decorators":[{"__symbolic":"call","expression":{"__symbolic":"reference","module":"@angular/core","name":"Component","line":2,"character":1},"arguments":[{"selector":"enl-randomer","template":"\n    <p>\n      randomer works!\n    </p>\n  ","styles":[]}]}],"members":{"__ctor__":[{"__symbolic":"constructor"}],"ngOnInit":[{"__symbolic":"method"}]}},"RandomerModule":{"__symbolic":"class","decorators":[{"__symbolic":"call","expression":{"__symbolic":"reference","module":"@angular/core","name":"NgModule","line":3,"character":1},"arguments":[{"imports":[],"declarations":[{"__symbolic":"reference","name":"RandomerComponent"}],"exports":[{"__symbolic":"reference","name":"RandomerComponent"}]}]}],"members":{}}},"origins":{"RandomerService":"./lib/randomer.service","RandomerComponent":"./lib/randomer.component","RandomerModule":"./lib/randomer.module"},"importAs":"randomer"}